setup.py
hiya/__init__.py
hiya.egg-info/PKG-INFO
hiya.egg-info/SOURCES.txt
hiya.egg-info/dependency_links.txt
hiya.egg-info/not-zip-safe
hiya.egg-info/top_level.txt