Metadata-Version: 1.0
Name: hiya
Version: 0.1
Summary: Identity Services over chff
Home-page: http://github.com/mnes-io/hiya
Author: Charles Perkins
Author-email: charlesap@gmail.com
License: MIT
Platform: UNKNOWN
